BeliX/__init__.py
BeliX/client.py
BeliX/creator.py
BeliX/message.py
BeliX-2.0.0.dist-info/LICENCE
BeliX-2.0.0.dist-info/METADATA
BeliX-2.0.0.dist-info/WHEEL
BeliX-2.0.0.dist-info/top_level.txt
BeliX-2.0.0.dist-info/RECORD
