Metadata-Version: 2.1
Name: BeliX
Version: 2.0.0
Summary: BeliX is a simple and fast Bale Messenger library built for you
Home-page: https://ble.ir/belix_py
Author: X_CODER
Author-email: x.coder.2721@gmail.com
License: MIT
Keywords: BeliX_library,messenger,python2,python,python3,api,self,BeliX,Bale,belix,BELIX,beli X,bale,bot,robot,library,balelib,balelibrary,bale.ai,BaleBot,Bale Api
Classifier: Programming Language :: Python :: 3.6
Classifier: Programming Language :: Python :: 3.7
Classifier: Programming Language :: Python :: 3.8
Classifier: Programming Language :: Python :: 3.9
Classifier: Programming Language :: Python :: 3.10
Classifier: Programming Language :: Python :: 3.11
Classifier: License :: OSI Approved :: MIT License
Requires-Python: ~=3.7
License-File: LICENCE
Requires-Dist: aiohttp
